cyb600_rk/__init__.py
cyb600_rk/main.py
rk_cyb600_lab1-1.0.8.data/scripts/datetime
rk_cyb600_lab1-1.0.8.dist-info/LICENSE
rk_cyb600_lab1-1.0.8.dist-info/METADATA
rk_cyb600_lab1-1.0.8.dist-info/WHEEL
rk_cyb600_lab1-1.0.8.dist-info/top_level.txt
rk_cyb600_lab1-1.0.8.dist-info/RECORD
