Metadata-Version: 2.1
Name: rk-cyb600-lab1
Version: 1.0.8
Summary: UNKNOWN
Home-page: UNKNOWN
Author: Riley Kourkounis
Author-email: kourkouk@canisius.edu
License: Apache License Version 2.0
Platform: UNKNOWN
License-File: LICENSE
Requires-Dist: Flask
